desktop_access_mcp_server/__init__.py
desktop_access_mcp_server/__main__.py
desktop_access_mcp_server/cli.py
desktop_access_mcp_server/cli_entry_point.py
desktop_access_mcp_server/desktop_controller.py
desktop_access_mcp_server/entry_point.py
desktop_access_mcp_server-0.1.1.dist-info/entry_points.txt
desktop_access_mcp_server-0.1.1.dist-info/licenses/LICENSE
desktop_access_mcp_server-0.1.1.dist-info/WHEEL
desktop_access_mcp_server-0.1.1.dist-info/METADATA
desktop_access_mcp_server-0.1.1.dist-info/RECORD
