Metadata-Version: 2.4
Name: desktop_access_mcp_server
Version: 0.1.1
Summary: desktop_access_mcp_server
Author-email: Hemang Joshi <hemangjoshi37a@gmail.com>
Requires-Python: >=3.8
License-Expression: MIT
License-File: LICENSE
Requires-Dist: mcp>=1.0.0
Requires-Dist: Pillow>=9.0.0
Requires-Dist: pynput>=1.7.0
Requires-Dist: mss>=9.0.0
Project-URL: Home, https://hjlabs.in
